{"Exif":{"Lat":0,"Long":0,"Date":"2024-11-28T16:46:15-08:00","Tags":{"ApertureValue":5.310704,"BrightnessValue":6.30625,"CustomRendered|int":"0","DateTimeDigitized|time.Time":"2024-11-28T16:46:15-08:00","DateTimeOriginal|time.Time":"2024-11-28T16:46:15-08:00","DateTime|time.Time":"2025-03-01T21:03:00-08:00","DigitalZoomRatio":1,"ExposureTime|*big.Rat":"1/2000","FNumber":6.3,"FileSource":"","FocalLength":326,"FocalLengthIn35mmFilm|int":"489","ISOSpeedRatings|int":"4000","ImageDescription":"Long-billed Curlew","LensModel":"FE 200-600mm F5.6-6.3 G OSS","LightSource|int":"0","Make":"SONY","MaxApertureValue":5.3125,"Model":"ILCE-1","SceneCaptureType|int":"0","SceneType":"","ShutterSpeedValue":10.965784,"Software":"Adobe Photoshop Lightroom Classic 13.2 (Windows)","SubSecTimeDigitized":"503","SubSecTimeOriginal":"503","XPTitle":[76,0,111,0,110,0,103,0,45,0,98,0,105,0,108,0,108,0,101,0,100,0,32,0,67,0,117,0,114,0,108,0,101,0,119,0,0,0]}}}
